watchmen_rest/__init__.py
watchmen_rest/auth_helper.py
watchmen_rest/authentication.py
watchmen_rest/cors.py
watchmen_rest/exceptions.py
watchmen_rest/logger/__init__.py
watchmen_rest/logger/mdc.py
watchmen_rest/logger/mdc_middleware.py
watchmen_rest/prometheus.py
watchmen_rest/rest_app.py
watchmen_rest/settings.py
watchmen_rest/system/__init__.py
watchmen_rest/system/health_router.py
watchmen_rest/util/__init__.py
watchmen_rest/util/raise_http_exception.py
watchmen_rest/util/validator.py
watchmen_rest-18.0.1.dist-info/METADATA
watchmen_rest-18.0.1.dist-info/WHEEL
watchmen_rest-18.0.1.dist-info/licenses/LICENSE
watchmen_rest-18.0.1.dist-info/RECORD
